[
  {
    "_id": "78fd61fb-40c4-47f3-bbb6-a5501815d3e0",
    "after_details": "Катехизація після Літургії: «Як розпізнавати Божу волю»",
    "after_time": "11:30",
    "auto_translated": true,
    "before_details": "Молитва на вервиці",
    "before_time": "09:30",
    "category": "liturgy",
    "date": "2025-10-25",
    "details": "Пам’ять св. апостола Луки. Особливі молитви за хворих.",
    "image": "https://cdn.sanity.io/images/y4j9iov2/production/9b81ae98c274dca1731f3a2667d35c945d4ee42e-1600x1066.jpg",
    "language": "uk",
    "link": "",
    "location": "Фрібур",
    "time": "10:00",
    "timestamp": "2025-10-23T08:41:00.000Z",
    "title": "Свята Літургія",
    "slug": "202510230841"
  },
  {
    "_id": "6f7b91a3-24eb-4e02-9ec8-5492a86534e3",
    "after_details": "уіуйцфцФявчас",
    "after_time": "11:30",
    "auto_translated": true,
    "before_details": "нкасгн",
    "before_time": "09:30",
    "category": "liturgy",
    "date": "2025-10-25",
    "details": "ормилормд",
    "image": "",
    "language": "uk",
    "link": "",
    "location": "лормлом",
    "time": "10:00",
    "timestamp": "2025-10-22T20:04:00.000Z",
    "title": "итор",
    "slug": "202510222004"
  },
  {
    "_id": "04b46557-85e4-4a50-ad2b-998a20911dba",
    "after_details": "Чаювання",
    "after_time": "1600",
    "auto_translated": true,
    "before_details": "Сповідь",
    "before_time": "9ІВ",
    "category": "liturgy",
    "date": "2025-10-25",
    "details": "Служба",
    "image": "https://cdn.sanity.io/images/y4j9iov2/production/96cbc38e05fe0753976e6ccd4453805a82fc7fd2-1024x1024.png",
    "language": "uk",
    "link": "",
    "location": "Лозанна",
    "time": "10:00",
    "timestamp": "2025-10-22T18:08:00.000Z",
    "title": "10іваип",
    "slug": "202510221808"
  },
  {
    "_id": "78fd61fb-40c4-47f3-bbb6-a5501815d3e0",
    "after_details": "Катехизація після Літургії: «Як розпізнавати Божу волю»",
    "after_time": "11:30",
    "auto_translated": true,
    "before_details": "Молитва на вервиці",
    "before_time": "09:30",
    "category": "liturgy",
    "date": "2025-10-25",
    "details": "Пам’ять св. апостола Луки. Особливі молитви за хворих.",
    "image": "https://cdn.sanity.io/images/y4j9iov2/production/9b81ae98c274dca1731f3a2667d35c945d4ee42e-1600x1066.jpg",
    "language": "en",
    "link": "",
    "location": "Фрібур",
    "time": "10:00",
    "timestamp": "2025-10-23T08:41:00.000Z",
    "title": "Свята Літургія",
    "slug": "202510230841"
  },
  {
    "_id": "78fd61fb-40c4-47f3-bbb6-a5501815d3e0",
    "after_details": "Катехизація після Літургії: «Як розпізнавати Божу волю»",
    "after_time": "11:30",
    "auto_translated": true,
    "before_details": "Молитва на вервиці",
    "before_time": "09:30",
    "category": "liturgy",
    "date": "2025-10-25",
    "details": "Пам’ять св. апостола Луки. Особливі молитви за хворих.",
    "image": "https://cdn.sanity.io/images/y4j9iov2/production/9b81ae98c274dca1731f3a2667d35c945d4ee42e-1600x1066.jpg",
    "language": "fr",
    "link": "",
    "location": "Фрібур",
    "time": "10:00",
    "timestamp": "2025-10-23T08:41:00.000Z",
    "title": "Свята Літургія",
    "slug": "202510230841"
  },
  {
    "_id": "6f7b91a3-24eb-4e02-9ec8-5492a86534e3",
    "after_details": "уіуйцфцФявчас",
    "after_time": "11:30",
    "auto_translated": true,
    "before_details": "нкасгн",
    "before_time": "09:30",
    "category": "liturgy",
    "date": "2025-10-25",
    "details": "ормилормд",
    "image": "",
    "language": "en",
    "link": "",
    "location": "лормлом",
    "time": "10:00",
    "timestamp": "2025-10-22T20:04:00.000Z",
    "title": "итор",
    "slug": "202510222004"
  },
  {
    "_id": "6f7b91a3-24eb-4e02-9ec8-5492a86534e3",
    "after_details": "уіуйцфцФявчас",
    "after_time": "11:30",
    "auto_translated": true,
    "before_details": "нкасгн",
    "before_time": "09:30",
    "category": "liturgy",
    "date": "2025-10-25",
    "details": "ормилормд",
    "image": "",
    "language": "fr",
    "link": "",
    "location": "лормлом",
    "time": "10:00",
    "timestamp": "2025-10-22T20:04:00.000Z",
    "title": "итор",
    "slug": "202510222004"
  },
  {
    "_id": "04b46557-85e4-4a50-ad2b-998a20911dba",
    "after_details": "Чаювання",
    "after_time": "1600",
    "auto_translated": true,
    "before_details": "Сповідь",
    "before_time": "9ІВ",
    "category": "liturgy",
    "date": "2025-10-25",
    "details": "Служба",
    "image": "https://cdn.sanity.io/images/y4j9iov2/production/96cbc38e05fe0753976e6ccd4453805a82fc7fd2-1024x1024.png",
    "language": "en",
    "link": "",
    "location": "Лозанна",
    "time": "10:00",
    "timestamp": "2025-10-22T18:08:00.000Z",
    "title": "10іваип",
    "slug": "202510221808"
  },
  {
    "_id": "04b46557-85e4-4a50-ad2b-998a20911dba",
    "after_details": "Чаювання",
    "after_time": "1600",
    "auto_translated": true,
    "before_details": "Сповідь",
    "before_time": "9ІВ",
    "category": "liturgy",
    "date": "2025-10-25",
    "details": "Служба",
    "image": "https://cdn.sanity.io/images/y4j9iov2/production/96cbc38e05fe0753976e6ccd4453805a82fc7fd2-1024x1024.png",
    "language": "fr",
    "link": "",
    "location": "Лозанна",
    "time": "10:00",
    "timestamp": "2025-10-22T18:08:00.000Z",
    "title": "10іваип",
    "slug": "202510221808"
  }
]